bai2/__init__.py
bai2/bai2.py
bai2/constants.py
bai2/exceptions.py
bai2/helpers.py
bai2/models.py
bai2/parsers.py
bai2/utils.py
bai2/writers.py
bai2-0.15.0.dist-info/licenses/LICENSE.txt
bai2-0.15.0.dist-info/METADATA
bai2-0.15.0.dist-info/WHEEL
bai2-0.15.0.dist-info/top_level.txt
bai2-0.15.0.dist-info/RECORD
